luna_variables/__init__.py
luna_variables/variables.py
luna_variables-0.0.2.dist-info/METADATA
luna_variables-0.0.2.dist-info/WHEEL
luna_variables-0.0.2.dist-info/top_level.txt
luna_variables-0.0.2.dist-info/RECORD
