Metadata-Version: 2.1
Name: luna-variables
Version: 0.0.2
Summary: A package of commonly used variables in luna
Home-page: https://github.com/username/your-repo
Author: Rugved
Author-email: rugveddanej.mail@gmail.com
Classifier: Programming Language :: Python :: 3
Classifier: License :: OSI Approved :: MIT License
Classifier: Operating System :: OS Independent
Requires-Python: >=3.6
